PureFlow/PureFlow.py
PureFlow/__init__.py
PureFlow-1.0.1.dist-info/LICENSE.txt
PureFlow-1.0.1.dist-info/METADATA
PureFlow-1.0.1.dist-info/WHEEL
PureFlow-1.0.1.dist-info/top_level.txt
PureFlow-1.0.1.dist-info/RECORD
